advent/__init__.py
advent/__main__.py
advent/errors.py
advent/functions.py
advent/parser.py
advent-1.0.3.dist-info/LICENSE
advent-1.0.3.dist-info/METADATA
advent-1.0.3.dist-info/WHEEL
advent-1.0.3.dist-info/entry_points.txt
advent-1.0.3.dist-info/top_level.txt
advent-1.0.3.dist-info/RECORD
