Metadata-Version: 2.1
Name: advent
Version: 1.0.3
Summary: Get your Advent of Code puzzle input and much more!
Author-email: ravilnicki <ravilnicki@gmail.com>
License: MIT License
Classifier: License :: OSI Approved :: MIT License
Classifier: Programming Language :: Python
Classifier: Programming Language :: Python :: 3
Requires-Python: >=3.10
License-File: LICENSE
Requires-Dist: python-dotenv >=1.0.0
